testbench/sliding_window/line_buffer1.v
module line_buffer1 #(
    parameter DATA_WIDTH = 8,
    parameter IMG_WIDTH  = 28
)(
    input  wire                   clk,
    input  wire                   rst_n,

    input  wire                   pixel_valid,
    input  wire [DATA_WIDTH-1:0]  pixel_in,

    // dữ liệu 3 hàng song song 
    output wire [DATA_WIDTH-1:0]  row0_pixel, // Hàng trên cùng (Cũ nhất - delay 2 dòng)
    output wire [DATA_WIDTH-1:0]  row1_pixel, // Hàng giữa     (delay 1 dòng)
    output wire [DATA_WIDTH-1:0]  row2_pixel, // Hàng dưới cùng (Hiện tại - không delay)

    // Tín hiệu đồng bộ trạng thái cấp cho window_generator
    output reg                    rows_valid, // Lên 1 ngay tại pixel đầu tiên của hàng thứ 3
    output reg                    new_row     // Xung báo chuyển hàng, tích cực tại Clock N+1 an toàn (Cách 1)
);

    // Sử dụng 2 mảng thanh ghi abstract để lưu trữ dữ liệu của 2 hàng trước đó
    reg [DATA_WIDTH-1:0] mem_line0 [0:IMG_WIDTH-1];
    reg [DATA_WIDTH-1:0] mem_line1 [0:IMG_WIDTH-1];

    // Bộ đếm vị trí cột logic nội bộ (0 đến IMG_WIDTH-1)
    reg [$clog2(IMG_WIDTH)-1:0] col_cnt;

    // Bộ đếm giai đoạn hàng để quản lý rows_valid
    // 0: Đang nạp hàng 0; 1: Đang nạp hàng 1; 2: Từ hàng 2 trở đi (Đủ dữ liệu)
    reg [1:0] row_phase;

    // Cờ báo hiệu đã xử lý xong pixel cuối cùng của hàng (tại Clock N)
    reg row_end_tick;

    // =========================================================================
    // CƠ CHẾ READ-BEFORE-WRITE (ĐỒNG BỘ THẲNG CỘT TUYỆT ĐỐI)
    // =========================================================================
    // Sử dụng mạch tổ hợp assign để lấy dữ liệu cũ ra truoc khi bị ghi đè tại cạnh lên clock.
    // Đảm bảo tại chu kỳ xử lý, cả 3 hàng đều chung một chỉ số cột logic `col_cnt`.
    assign row2_pixel = pixel_in;
    assign row1_pixel = mem_line1[col_cnt];
    assign row0_pixel = mem_line0[col_cnt];

    // =========================================================================
    // LOGIC ĐIỀU KHIỂN HÀNG VÀ ĐỒNG BỘ
    // =========================================================================
    integer i;
    always @(posedge clk or negedge rst_n) begin
        if (!rst_n) begin
            col_cnt      <= 0;
            row_phase    <= 2'b00;
            row_end_tick <= 1'b0;
            new_row      <= 1'b0;
            rows_valid   <= 1'b0;
            
            // Xóa mảng thanh ghi khi reset để tránh rác mô phỏng
            for (i = 0; i < IMG_WIDTH; i = i + 1) begin
                mem_line0[i] <= {DATA_WIDTH{1'b0}};
                mem_line1[i] <= {DATA_WIDTH{1'b0}};
            end
        end else begin
            // Tạo xung chuyển hàng an toàn ở chu kỳ N+1 (Cách 1)
            if (row_end_tick) begin
                new_row      <= 1'b1;
                row_end_tick <= 1'b0;
            end else begin
                new_row      <= 1'b0;
            end

            // Xử lý luồng dữ liệu stream
            if (pixel_valid) begin
                // Tiến hành ghi dịch chuyển dữ liệu theo chiều dọc vào mảng thanh ghi
                mem_line1[col_cnt] <= pixel_in;          // Nạp pixel hiện tại vào hàng giữa
                mem_line0[col_cnt] <= mem_line1[col_cnt]; // Đẩy pixel cũ của hàng giữa lên hàng trên cùng

                // Quản lý bộ đếm vị trí không gian
                if (col_cnt == IMG_WIDTH - 1) begin
                    col_cnt      <= 0;
                    row_end_tick <= 1'b1; // Đánh dấu đã nhận xong ô cuoi của một hàng tại Clock N
                    
                    // Tăng phase quản lý hàng (Bão hòa tại phase 2)
                    if (row_phase < 2'b10) begin
                        row_phase <= row_phase + 1'b1;
                    end
                end else begin
                    col_cnt      <= col_cnt + 1'b1;
                    row_end_tick <= 1'b0;
                end
            end

            // Khi kết thúc hàng thứ 2 (Hàng 1), row_phase cập nhật lên bằng 2.
            // Đúng chu kỳ tiếp theo, khi pixel_valid = 1 của hàng thứ 3 (Hàng 2) vừa chui vào, 
            // rows_valid vọt lên 1 chuẩn chỉ từ pixel đầu tiên của hàng 3.
            if (pixel_valid && (row_phase == 2'b10)) begin
                rows_valid <= 1'b1; // khi đã có 2 hàng trước đó
            end else begin
                rows_valid <= 1'b0;
            end
        end
    end

endmodule

testbench/sliding_window/tb_line_buffer1.v
`timescale 1ns/1ps

module tb_line_buffer;

    parameter DATA_WIDTH = 8;
    parameter IMG_WIDTH  = 6;
    parameter IMG_HEIGHT = 6;

    reg clk;
    reg rst_n;

    reg pixel_valid;
    reg [DATA_WIDTH-1:0] pixel_in;

    wire [DATA_WIDTH-1:0] row0_pixel;
    wire [DATA_WIDTH-1:0] row1_pixel;
    wire [DATA_WIDTH-1:0] row2_pixel;

    wire rows_valid;
    wire new_row;


    // ============================================================
    // DUT
    // ============================================================

    line_buffer1 #(
        .DATA_WIDTH(DATA_WIDTH),
        .IMG_WIDTH(IMG_WIDTH)
    )
    u_dut (
        .clk(clk),
        .rst_n(rst_n),

        .pixel_valid(pixel_valid),
        .pixel_in(pixel_in),

        .row0_pixel(row0_pixel),
        .row1_pixel(row1_pixel),
        .row2_pixel(row2_pixel),

        .rows_valid(rows_valid),
        .new_row(new_row)
    );


    // ============================================================
    // CLOCK
    // ============================================================

    initial begin
        clk = 1'b0;

        forever #5 clk = ~clk;
    end


    // ============================================================
    // SEND ONE PIXEL
    // ============================================================

    task send_pixel;

        input integer row;
        input integer col;

        begin

            @(negedge clk);

            pixel_valid = 1'b1;

            pixel_in = row * 10 + col;


            @(posedge clk);

            #1;


            $display(
                "TIME=%0t | ROW=%0d | COL=%0d | IN=%0d | ROW0=%0d | ROW1=%0d | ROW2=%0d | ROWS_VALID=%b | NEW_ROW=%b",
                $time,
                row,
                col,
                pixel_in,
                row0_pixel,
                row1_pixel,
                row2_pixel,
                rows_valid,
                new_row
            );

        end

    endtask


    // ============================================================
    // SEND ONE ROW
    // ============================================================

    task send_row;

        input integer row;

        integer col;

        begin

            $display("");
            $display("==================================================");
            $display("START ROW %0d", row);
            $display("==================================================");


            for (col = 0; col < IMG_WIDTH; col = col + 1) begin

                send_pixel(row, col);
            end


            // Ngắt valid giữa hai hàng
            @(negedge clk);

            pixel_valid = 1'b0;

            pixel_in = 0;


            @(posedge clk);

            #1;


            $display("");
            $display("END ROW %0d", row);

            $display(
                "INTERNAL: col_cnt=%0d | row_phase=%0d | row_end_tick=%b",
                u_dut.col_cnt,
                u_dut.row_phase,
                u_dut.row_end_tick
            );

            $display(
                "CONTROL: rows_valid=%b | new_row=%b",
                rows_valid,
                new_row
            );

        end

    endtask


    // ============================================================
    // MAIN TEST
    // ============================================================

    integer r;


    initial begin

        rst_n = 1'b0;

        pixel_valid = 1'b0;

        pixel_in = 0;


        $display("");
        $display("==================================================");
        $display("RESET");
        $display("==================================================");


        #20;

        rst_n = 1'b1;


        $display("");
        $display("##################################################");
        $display("START 6x6 IMAGE");
        $display("##################################################");


        for (r = 0; r < IMG_HEIGHT; r = r + 1) begin

            send_row(r);

        end


        #20;


        $display("");
        $display("##################################################");
        $display("SIMULATION COMPLETE");
        $display("##################################################");


        $finish;

    end


    // ============================================================
    // WAVEFORM
    // ============================================================

    initial begin

        $dumpfile("tb_line_buffer.vcd");

        $dumpvars(
            0,
            tb_line_buffer
        );

    end


endmodule

testbench/sliding_window/simulation/modelsim/tb_line_buffer.vcd
$date
	Tue Jul 21 15:39:16 2026
$end
$version
	ModelSim Version 10.5b
$end
$timescale
	1ps
$end

$scope module tb_line_buffer $end
$var parameter 32 ! DATA_WIDTH $end
$var parameter 32 " IMG_WIDTH $end
$var parameter 32 # IMG_HEIGHT $end
$var reg 1 $ clk $end
$var reg 1 % rst_n $end
$var reg 1 & pixel_valid $end
$var reg 8 ' pixel_in [7:0] $end
$var wire 1 ( row0_pixel [7] $end
$var wire 1 ) row0_pixel [6] $end
$var wire 1 * row0_pixel [5] $end
$var wire 1 + row0_pixel [4] $end
$var wire 1 , row0_pixel [3] $end
$var wire 1 - row0_pixel [2] $end
$var wire 1 . row0_pixel [1] $end
$var wire 1 / row0_pixel [0] $end
$var wire 1 0 row1_pixel [7] $end
$var wire 1 1 row1_pixel [6] $end
$var wire 1 2 row1_pixel [5] $end
$var wire 1 3 row1_pixel [4] $end
$var wire 1 4 row1_pixel [3] $end
$var wire 1 5 row1_pixel [2] $end
$var wire 1 6 row1_pixel [1] $end
$var wire 1 7 row1_pixel [0] $end
$var wire 1 8 row2_pixel [7] $end
$var wire 1 9 row2_pixel [6] $end
$var wire 1 : row2_pixel [5] $end
$var wire 1 ; row2_pixel [4] $end
$var wire 1 < row2_pixel [3] $end
$var wire 1 = row2_pixel [2] $end
$var wire 1 > row2_pixel [1] $end
$var wire 1 ? row2_pixel [0] $end
$var wire 1 @ rows_valid $end
$var wire 1 A new_row $end
$var integer 32 B r $end

$scope task send_pixel $end
$var integer 32 C row $end
$var integer 32 D col $end
$upscope $end

$scope task send_row $end
$var integer 32 E row $end
$var integer 32 F col $end
$upscope $end

$scope module u_dut $end
$var parameter 32 G DATA_WIDTH $end
$var parameter 32 H IMG_WIDTH $end
$var wire 1 I clk $end
$var wire 1 J rst_n $end
$var wire 1 K pixel_valid $end
$var wire 1 L pixel_in [7] $end
$var wire 1 M pixel_in [6] $end
$var wire 1 N pixel_in [5] $end
$var wire 1 O pixel_in [4] $end
$var wire 1 P pixel_in [3] $end
$var wire 1 Q pixel_in [2] $end
$var wire 1 R pixel_in [1] $end
$var wire 1 S pixel_in [0] $end
$var wire 1 ( row0_pixel [7] $end
$var wire 1 ) row0_pixel [6] $end
$var wire 1 * row0_pixel [5] $end
$var wire 1 + row0_pixel [4] $end
$var wire 1 , row0_pixel [3] $end
$var wire 1 - row0_pixel [2] $end
$var wire 1 . row0_pixel [1] $end
$var wire 1 / row0_pixel [0] $end
$var wire 1 0 row1_pixel [7] $end
$var wire 1 1 row1_pixel [6] $end
$var wire 1 2 row1_pixel [5] $end
$var wire 1 3 row1_pixel [4] $end
$var wire 1 4 row1_pixel [3] $end
$var wire 1 5 row1_pixel [2] $end
$var wire 1 6 row1_pixel [1] $end
$var wire 1 7 row1_pixel [0] $end
$var wire 1 8 row2_pixel [7] $end
$var wire 1 9 row2_pixel [6] $end
$var wire 1 : row2_pixel [5] $end
$var wire 1 ; row2_pixel [4] $end
$var wire 1 < row2_pixel [3] $end
$var wire 1 = row2_pixel [2] $end
$var wire 1 > row2_pixel [1] $end
$var wire 1 ? row2_pixel [0] $end
$var reg 1 T rows_valid $end
$var reg 1 U new_row $end
$var reg 3 V col_cnt [2:0] $end
$var reg 2 W row_phase [1:0] $end
$var reg 1 X row_end_tick $end
$var integer 32 Y i $end
$upscope $end
$upscope $end
$enddefinitions $end
#0
$dumpvars
0$
0%
0&
b0 '
0T
0U
b0 V
b0 W
0X
b1000 !
b110 "
b110 #
b1000 G
b110 H
b110 Y
bx C
bx D
bx E
bx F
bx B
0/
0.
0-
0,
0+
0*
0)
0(
07
06
05
04
03
02
01
00
0?
0>
0=
0<
0;
0:
09
08
0@
0A
0S
0R
0Q
0P
0O
0N
0M
0L
0K
0J
0I
$end
#5000
1$
1I
b0 Y
b1 Y
b10 Y
b11 Y
b100 Y
b101 Y
b110 Y
#10000
0$
0I
#15000
1$
1I
b0 Y
b1 Y
b10 Y
b11 Y
b100 Y
b101 Y
b110 Y
#20000
1%
b0 B
b0 E
b0 F
b0 C
b0 D
0$
1J
0I
1&
1K
#25000
1$
1I
b1 V
#26000
b1 F
b1 D
#30000
0$
0I
b1 '
1S
1?
#35000
1$
1I
b10 V
#36000
b10 F
b10 D
#40000
0$
0I
b10 '
0S
1R
0?
1>
#45000
1$
1I
b11 V
#46000
b11 F
b11 D
#50000
0$
0I
b11 '
1S
1?
#55000
1$
1I
b100 V
#56000
b100 F
b100 D
#60000
0$
0I
b100 '
0S
0R
1Q
0?
0>
1=
#65000
1$
1I
b101 V
#66000
b101 F
b101 D
#70000
0$
0I
b101 '
1S
1?
#75000
1$
1I
b0 V
1X
b1 W
#76000
b110 F
#80000
0$
0I
0&
b0 '
0K
0S
0Q
0?
0=
#85000
1$
1I
1U
0X
1A
#86000
b1 B
b1 E
b0 F
b1 C
b0 D
#90000
0$
0I
1&
b1010 '
1K
1R
1P
1>
1<
#95000
1$
1I
0U
b1 V
0A
17
#96000
b1 F
b1 D
#100000
0$
0I
b1011 '
1S
1?
#105000
1$
1I
b10 V
07
16
#106000
b10 F
b10 D
#110000
0$
0I
b1100 '
0S
0R
1Q
0?
0>
1=
#115000
1$
1I
b11 V
17
#116000
b11 F
b11 D
#120000
0$
0I
b1101 '
1S
1?
#125000
1$
1I
b100 V
07
06
15
#126000
b100 F
b100 D
#130000
0$
0I
b1110 '
0S
1R
0?
1>
#135000
1$
1I
b101 V
17
#136000
b101 F
b101 D
#140000
0$
0I
b1111 '
1S
1?
#145000
1$
1I
b0 V
1X
b10 W
07
16
05
14
#146000
b110 F
#150000
0$
0I
0&
b0 '
0K
0S
0R
0Q
0P
0?
0>
0=
0<
#155000
1$
1I
1U
0X
1A
#156000
b10 B
b10 E
b0 F
b10 C
b0 D
#160000
0$
0I
1&
b10100 '
1K
1Q
1O
1=
1;
#165000
1$
1I
0U
b1 V
1T
0A
1/
17
1@
#166000
b1 F
b1 D
#170000
0$
0I
b10101 '
1S
1?
#175000
1$
1I
b10 V
0/
1.
07
06
15
#176000
b10 F
b10 D
#180000
0$
0I
b10110 '
0S
1R
0?
1>
#185000
1$
1I
b11 V
1/
17
#186000
b11 F
b11 D
#190000
0$
0I
b10111 '
1S
1?
#195000
1$
1I
b100 V
0/
0.
1-
07
16
#196000
b100 F
b100 D
#200000
0$
0I
b11000 '
0S
0R
0Q
1P
0?
0>
0=
1<
#205000
1$
1I
b101 V
1/
17
#206000
b101 F
b101 D
#210000
0$
0I
b11001 '
1S
1?
#215000
1$
1I
b0 V
1X
0/
1.
0-
1,
07
06
04
13
#216000
b110 F
#220000
0$
0I
0&
b0 '
0K
0S
0P
0O
0?
0<
0;
#225000
1$
1I
1U
0X
0T
1A
0@
#226000
b11 B
b11 E
b0 F
b11 C
b0 D
#230000
0$
0I
1&
b11110 '
1K
1R
1Q
1P
1O
1>
1=
1<
1;
#235000
1$
1I
0U
b1 V
1T
0A
1/
17
1@
#236000
b1 F
b1 D
#240000
0$
0I
b11111 '
1S
1?
#245000
1$
1I
b10 V
0/
0.
1-
07
16
#246000
b10 F
b10 D
#250000
0$
0I
b100000 '
0S
0R
0Q
0P
0O
1N
0?
0>
0=
0<
0;
1:
#255000
1$
1I
b11 V
1/
17
#256000
b11 F
b11 D
#260000
0$
0I
b100001 '
1S
1?
#265000
1$
1I
b100 V
0/
1.
07
06
05
14
#266000
b100 F
b100 D
#270000
0$
0I
b100010 '
0S
1R
0?
1>
#275000
1$
1I
b101 V
1/
17
#276000
b101 F
b101 D
#280000
0$
0I
b100011 '
1S
1?
#285000
1$
1I
b0 V
1X
0/
0.
0,
1+
07
16
15
#286000
b110 F
#290000
0$
0I
0&
b0 '
0K
0S
0R
0N
0?
0>
0:
#295000
1$
1I
1U
0X
0T
1A
0@
#296000
b100 B
b100 E
b0 F
b100 C
b0 D
#300000
0$
0I
1&
b101000 '
1K
1P
1N
1<
1:
#305000
1$
1I
0U
b1 V
1T
0A
1/
17
1@
#306000
b1 F
b1 D
#310000
0$
0I
b101001 '
1S
1?
#315000
1$
1I
b10 V
0/
1.
07
06
05
04
03
12
#316000
b10 F
b10 D
#320000
0$
0I
b101010 '
0S
1R
0?
1>
#325000
1$
1I
b11 V
1/
17
#326000
b11 F
b11 D
#330000
0$
0I
b101011 '
1S
1?
#335000
1$
1I
b100 V
0/
0.
0-
1,
07
16
#336000
b100 F
b100 D
#340000
0$
0I
b101100 '
0S
0R
1Q
0?
0>
1=
#345000
1$
1I
b101 V
1/
17
#346000
b101 F
b101 D
#350000
0$
0I
b101101 '
1S
1?
#355000
1$
1I
b0 V
1X
0/
1.
1-
07
06
14
#356000
b110 F
#360000
0$
0I
0&
b0 '
0K
0S
0Q
0P
0N
0?
0=
0<
0:
#365000
1$
1I
1U
0X
0T
1A
0@
#366000
b101 B
b101 E
b0 F
b101 C
b0 D
#370000
0$
0I
1&
b110010 '
1K
1R
1O
1N
1>
1;
1:
#375000
1$
1I
0U
b1 V
1T
0A
1/
17
1@
#376000
b1 F
b1 D
#380000
0$
0I
b110011 '
1S
1?
#385000
1$
1I
b10 V
0/
0.
0-
0,
0+
1*
07
16
#386000
b10 F
b10 D
#390000
0$
0I
b110100 '
0S
0R
1Q
0?
0>
1=
#395000
1$
1I
b11 V
1/
17
#396000
b11 F
b11 D
#400000
0$
0I
b110101 '
1S
1?
#405000
1$
1I
b100 V
0/
1.
07
06
15
#406000
b100 F
b100 D
#410000
0$
0I
b110110 '
0S
1R
0?
1>
#415000
1$
1I
b101 V
1/
17
#416000
b101 F
b101 D
#420000
0$
0I
b110111 '
1S
1?
#425000
1$
1I
b0 V
1X
0/
0.
1,
07
16
05
04
13
#426000
b110 F
#430000
0$
0I
0&
b0 '
0K
0S
0R
0Q
0O
0N
0?
0>
0=
0;
0:
#435000
1$
1I
1U
0X
0T
1A
0@
#436000
b110 B
#440000
0$
0I
#445000
1$
1I
0U
0A
